carbon_webapplication/__init__.py
carbon_webapplication/dtos/__init__.py
carbon_webapplication/dtos/permission.py
carbon_webapplication/dtos/request.py
carbon_webapplication/dtos/user.py
carbon_webapplication/enums/__init__.py
carbon_webapplication/enums/header_names.py
carbon_webapplication/httpclient/__init__.py
carbon_webapplication/httpclient/auth_httpclient_factory.py
carbon_webapplication/middlewares/__init__.py
carbon_webapplication/middlewares/bearer_token_middleware.py
carbon_webapplication/tenant_management/__init__.py
carbon_webapplication/tenant_management/tenant_management.py
carbon_webapplication-1.0.3.dist-info/METADATA
carbon_webapplication-1.0.3.dist-info/WHEEL
carbon_webapplication-1.0.3.dist-info/RECORD
